README.md
setup.py
sudoaptinstall/__init__.py
sudoaptinstall/sudoaptinstall.py
sudoaptinstall.egg-info/PKG-INFO
sudoaptinstall.egg-info/SOURCES.txt
sudoaptinstall.egg-info/dependency_links.txt
sudoaptinstall.egg-info/requires.txt
sudoaptinstall.egg-info/top_level.txt